pylgtv/__init__.py
pylgtv/endpoints.py
pylgtv/handshake.json
pylgtv/webos_client.py
pylgtv-0.1.9.dist-info/METADATA
pylgtv-0.1.9.dist-info/RECORD
pylgtv-0.1.9.dist-info/WHEEL
pylgtv-0.1.9.dist-info/top_level.txt
pylgtv-0.1.9.dist-info/zip-safe
