Metadata-Version: 2.1
Name: pylgtv
Version: 0.1.9
Summary: Library to control webOS based LG Tv devices
Home-page: https://github.com/TheRealLink/pylgtv
Author: Dennis Karpienski
Author-email: dennis@karpienski.de
License: UNKNOWN
Download-URL: https://github.com/TheRealLink/pylgtv/archive/0.1.9.tar.gz
Keywords: webos,tv
Platform: UNKNOWN
Requires-Dist: websockets
Requires-Dist: asyncio
